awsee/__init__.py
awsee/aws_credentials_parser.py
awsee/awseepy.py
awsee/awseestate.py
awsee/awsservices.py
awsee/completers_suggesters.py
awsee/emoticons.py
awsee/functions.py
awsee/general.py
awsee/logmanager.py
awsee/messages.py
awsee/mfamanager.py
awsee/preferences.py
awsee/prettytable.py
awsee/profilemanager.py
awsee/repository.py
awsee/rolemanager.py
awsee/sessioninfo.py
awsee/sessionmanager.py
awsee/style.py
awsee/tableargs.py
awsee/test.py
awsee/utils.py
awsee-0.0.28.data/scripts/awsee
awsee-0.0.28.data/scripts/awsee.bat
awsee-0.0.28.dist-info/METADATA
awsee-0.0.28.dist-info/WHEEL
awsee-0.0.28.dist-info/entry_points.txt
awsee-0.0.28.dist-info/top_level.txt
awsee-0.0.28.dist-info/RECORD
