Metadata-Version: 2.1
Name: awsee
Version: 0.0.28
Summary: Utility to help me manage my AWS CLI Session with Profiles, Roles and MFA
Home-page: https://ualter.github.io/awsee-site/
Author: Ualter Otoni Pereira
Author-email: ualter.junior@gmail.com
License: MIT
Keywords: aws,cloud,awsee,boto3,ec2,vpc
Platform: UNKNOWN
Classifier: Development Status :: 3 - Alpha
Classifier: Intended Audience :: Developers
Classifier: Intended Audience :: System Administrators
Classifier: License :: OSI Approved :: MIT License
Classifier: Programming Language :: Python :: 3.7
Classifier: Programming Language :: Python :: 3.8
Requires-Dist: Pygments (>=2.3.1)
Requires-Dist: XlsxWriter (>=1.3.7)
Requires-Dist: arnparse (>=0.0.2)
Requires-Dist: boto3 (>=1.18.62)
Requires-Dist: botocore (>=1.21.62)
Requires-Dist: clipboard (>=0.0.4)
Requires-Dist: prompt-toolkit (>=2.0.10)
Requires-Dist: pyreadline
Requires-Dist: python-dateutil (>=2.8.2)
Requires-Dist: pytz (>=2019.3)
Requires-Dist: tinydb (>=4.5.2)
